limlearn/__init__.py
limlearn/cv.py
limlearn/mlp.py
limlearn-1.0.0.dist-info/DESCRIPTION.rst
limlearn-1.0.0.dist-info/METADATA
limlearn-1.0.0.dist-info/RECORD
limlearn-1.0.0.dist-info/WHEEL
limlearn-1.0.0.dist-info/metadata.json
limlearn-1.0.0.dist-info/top_level.txt
