Metadata-Version: 2.0
Name: limlearn
Version: 1.0.0
Summary: Limit of Learning
Home-page: https://github.com/dem123456789
Author: Enmao Diao
Author-email: diao_em@hotmail.com
License: All Rights Reserved
Keywords: Artificial Intelligence,Limit of Learning
Platform: UNKNOWN
Classifier: Development Status :: 5 - Production/Stable
Classifier: Intended Audience :: Developers
Classifier: Topic :: Scientific/Engineering :: Artificial Intelligence
Classifier: License :: Free for non-commercial use
Classifier: Programming Language :: Python :: 2.7
Classifier: Programming Language :: Python :: 3.6
Requires-Dist: Theano (>=0.9.0)
Requires-Dist: scikit-learn (>=0.18)
